agent_flows/__init__.py
agent_flows/reason.py
agent_flows-0.1.0.dist-info/METADATA
agent_flows-0.1.0.dist-info/WHEEL
agent_flows-0.1.0.dist-info/entry_points.txt
agent_flows-0.1.0.dist-info/RECORD
