Metadata-Version: 2.4
Name: agent-flows
Version: 0.1.0
Summary: An frame work for reasoning
Requires-Python: >=3.13
Requires-Dist: openai>=1.95.1
